motifstudio_client/__init__.py
motifstudio_client-0.1.1.dist-info/METADATA
motifstudio_client-0.1.1.dist-info/WHEEL
motifstudio_client-0.1.1.dist-info/licenses/LICENSE
motifstudio_client-0.1.1.dist-info/RECORD
