Metadata-Version: 2.3
Name: motifstudio-client
Version: 0.1.1
Summary: Client library for the Motif Studio API
License-File: LICENSE
Requires-Python: >=3.11
Requires-Dist: httpx>=0.27.0
Requires-Dist: networkx>=3.3
Requires-Dist: pydantic>=2.8.2
